<?xml version="1.0" encoding="UTF-8"?>
<con:soapui-project id="0c608009-9796-472e-9d30-9a3e1bec84aa" created="3.53.0" activeEnvironment="Default environment" encryptionMode="Not encrypted" name="PetStoreRest" projectVersion="" updated="3.53.0 2024-05-13T12:06:25Z" xmlns:con="http://eviware.com/soapui/config">
  <con:settings/>
  <con:interface xsi:type="con:RestService" id="e648c6b6-6a11-4e14-abfe-1bc520296513" wadlVersion="http://wadl.dev.java.net/2009/02" name="https://petstore.swagger.io" type="rest" xmlns:xsi="http://www.w3.org/2001/XMLSchema-instance">
    <con:settings id="68bc4ad7-6f65-4671-98b0-725313886bfe"/>
    <con:definitionCache type="TEXT" rootPart=""/>
    <con:endpoints>
      <con:endpoint>https://petstore.swagger.io</con:endpoint>
    </con:endpoints>
    <con:resource name="Pet" path="/v2/pet" id="2180e279-cc74-4d7f-adc0-bbb3ba74e792">
      <con:settings/>
      <con:parameters/>
      <con:method name="Pet" id="1161a2ed-f2a5-44a6-8c88-4cbf3b7d5bef" method="POST">
        <con:settings/>
        <con:parameters/>
        <con:representation type="REQUEST">
          <con:mediaType>application/json</con:mediaType>
          <con:params/>
        </con:representation>
        <con:representation type="RESPONSE">
          <con:mediaType>application/json</con:mediaType>
          <con:status>200</con:status>
          <con:params/>
          <con:element xmlns:pet="https://petstore.swagger.io/v2/pet">pet:Response</con:element>
        </con:representation>
        <con:representation type="FAULT">
          <con:mediaType>application/json</con:mediaType>
          <con:status>400</con:status>
          <con:params/>
          <con:element xmlns:pet="https://petstore.swagger.io/v2/pet">pet:Fault</con:element>
        </con:representation>
        <con:request name="Request 1" id="28d15efd-6261-4047-bbc4-8a06c8f56396" mediaType="application/json">
          <con:settings/>
          <con:endpoint>https://petstore.swagger.io</con:endpoint>
          <con:credentials>
            <con:selectedAuthProfile>No Authorization</con:selectedAuthProfile>
            <con:authType>No Authorization</con:authType>
          </con:credentials>
          <con:parameters/>
        </con:request>
      </con:method>
    </con:resource>
    <con:resource name="FindByStatus" path="/v2/pet/findByStatus" id="ee54fa50-a5a1-4fc5-b4f5-f7164dbca4cb">
      <con:settings/>
      <con:parameters/>
      <con:method name="FindByStatus" id="6045d93f-b3bc-4132-9afc-72c194d91d2a" method="GET">
        <con:settings/>
        <con:parameters>
          <con:parameter required="true">
            <con:name>ststus</con:name>
            <con:value>alive</con:value>
            <con:style>QUERY</con:style>
            <con:default>alive</con:default>
            <con:path xsi:nil="true"/>
            <con:description xsi:nil="true"/>
          </con:parameter>
        </con:parameters>
        <con:representation type="RESPONSE">
          <con:mediaType>application/json</con:mediaType>
          <con:status>200</con:status>
          <con:params/>
          <con:element>Response</con:element>
        </con:representation>
        <con:request name="Request 1" id="5fe4087b-3b0b-4064-9f0a-7255a33e444d" mediaType="application/json">
          <con:settings/>
          <con:endpoint>https://petstore.swagger.io</con:endpoint>
          <con:credentials>
            <con:selectedAuthProfile>No Authorization</con:selectedAuthProfile>
            <con:authType>No Authorization</con:authType>
          </con:credentials>
          <con:parameters>
            <con:entry key="ststus" value="alive"/>
          </con:parameters>
          <con:parameterOrder>
            <con:entry>ststus</con:entry>
          </con:parameterOrder>
        </con:request>
      </con:method>
    </con:resource>
    <con:resource name="PetId" path="/v2/pet/{petId}" id="fee0997d-34dd-48e7-b9b0-6db1fa8bc18f">
      <con:settings/>
      <con:parameters/>
      <con:method name="PetId" id="dd70b4d8-d0c1-4d6d-8f84-b49a6aca6206" method="DELETE">
        <con:settings/>
        <con:parameters>
          <con:parameter required="true">
            <con:name>petId</con:name>
            <con:value>petId</con:value>
            <con:style>TEMPLATE</con:style>
            <con:default>petId</con:default>
            <con:path xsi:nil="true"/>
            <con:description xsi:nil="true"/>
          </con:parameter>
        </con:parameters>
        <con:representation type="RESPONSE">
          <con:mediaType>application/json</con:mediaType>
          <con:status>200</con:status>
          <con:params/>
          <con:element xmlns:ns="https://petstore.swagger.io/v2/pet/77654">ns:Response</con:element>
        </con:representation>
        <con:representation type="REQUEST">
          <con:mediaType>application/json</con:mediaType>
          <con:params/>
        </con:representation>
        <con:request name="Request 1" id="9a8337f8-40e9-4ff5-bbcd-0dd6bfb304bc" mediaType="application/json">
          <con:settings/>
          <con:endpoint>https://petstore.swagger.io</con:endpoint>
          <con:credentials>
            <con:selectedAuthProfile>No Authorization</con:selectedAuthProfile>
            <con:authType>No Authorization</con:authType>
          </con:credentials>
          <con:parameters>
            <con:entry key="petId" value="petId"/>
          </con:parameters>
          <con:parameterOrder>
            <con:entry>petId</con:entry>
          </con:parameterOrder>
        </con:request>
      </con:method>
    </con:resource>
  </con:interface>
  <con:testSuite id="8b9d18fa-878e-4fda-98ce-de09c9dd348f" name="https://petstore.swagger.io Test Suite">
    <con:settings id="f74dff39-c791-4b44-a07a-ffa56e308dcc"/>
    <con:runType>SEQUENTIAL</con:runType>
    <con:testCase id="cb80b1cf-d5b3-4372-b18d-a8389d725231" discardOkResults="false" failOnError="false" failTestCaseOnErrors="true" keepSession="false" name="Test Case" searchProperties="true" timeout="0">
      <con:settings/>
      <con:testStep type="restrequest" name="POST" id="d5efd79f-9665-4bf6-a70e-e05b09868312">
        <con:settings/>
        <con:config service="https://petstore.swagger.io" resourcePath="/v2/pet" methodName="Pet" xsi:type="con:RestRequestStep" xmlns:xsi="http://www.w3.org/2001/XMLSchema-instance">
          <con:restRequest name="POST" id="28d15efd-6261-4047-bbc4-8a06c8f56396" mediaType="application/json" postQueryString="false">
            <con:settings>
              <con:setting id="com.eviware.soapui.impl.wsdl.WsdlRequest@request-headers">&lt;xml-fragment/></con:setting>
            </con:settings>
            <con:endpoint>https://petstore.swagger.io</con:endpoint>
            <con:request>{
    "id": 77654,
    "name": "Pandu",
    "status": "available"
}</con:request>
            <con:originalUri>https://petstore.swagger.io/v2/pet</con:originalUri>
            <con:assertion type="Valid HTTP Status Codes" id="da4561b1-0e77-4ef5-a0b5-2a9a97d34f49" name="Valid HTTP Status Codes">
              <con:settings/>
              <con:configuration>
                <codes>200</codes>
              </con:configuration>
            </con:assertion>
            <con:assertion type="JsonPath Match" id="82ca02e0-cddd-4dd1-8ca0-45e6fbd95d89" name="JSONPath Match">
              <con:configuration>
                <path>$['status']</path>
                <content>available</content>
                <allowWildcards>false</allowWildcards>
                <ignoreNamspaceDifferences>false</ignoreNamspaceDifferences>
                <ignoreComments>false</ignoreComments>
              </con:configuration>
            </con:assertion>
            <con:credentials>
              <con:selectedAuthProfile>No Authorization</con:selectedAuthProfile>
              <con:authType>No Authorization</con:authType>
            </con:credentials>
            <con:jmsConfig JMSDeliveryMode="PERSISTENT"/>
            <con:parameters/>
          </con:restRequest>
        </con:config>
      </con:testStep>
      <con:testStep type="transfer" name="Property Transfer" id="5eb7db3a-81ac-4579-a3cd-d712709ad7d5">
        <con:settings/>
        <con:config xsi:type="con:PropertyTransfersStep" xmlns:xsi="http://www.w3.org/2001/XMLSchema-instance">
          <con:transfers setNullOnMissingSource="true" transferTextContent="true" failOnError="true" ignoreEmpty="false" transferToAll="false" entitize="false" transferChildNodes="false">
            <con:name>statusTransfer</con:name>
            <con:sourceType>Response</con:sourceType>
            <con:sourceStep>POST</con:sourceStep>
            <con:sourcePath>$['status']</con:sourcePath>
            <con:targetType>ststus</con:targetType>
            <con:targetStep>GET</con:targetStep>
            <con:targetPath/>
            <con:type>JSONPATH</con:type>
            <con:upgraded>true</con:upgraded>
          </con:transfers>
          <con:transfers setNullOnMissingSource="true" transferTextContent="true" failOnError="true" ignoreEmpty="false" transferToAll="false" entitize="false" transferChildNodes="false">
            <con:name>idTransfer</con:name>
            <con:sourceType>Response</con:sourceType>
            <con:sourceStep>POST</con:sourceStep>
            <con:sourcePath>$['id']</con:sourcePath>
            <con:targetType>petId</con:targetType>
            <con:targetStep>DELETE</con:targetStep>
            <con:type>JSONPATH</con:type>
            <con:upgraded>true</con:upgraded>
          </con:transfers>
        </con:config>
      </con:testStep>
      <con:testStep type="restrequest" name="GET" id="5ffc0454-92f1-4193-99ed-9dde02acd9bd">
        <con:settings/>
        <con:config service="https://petstore.swagger.io" resourcePath="/v2/pet/findByStatus" methodName="FindByStatus" xsi:type="con:RestRequestStep" xmlns:xsi="http://www.w3.org/2001/XMLSchema-instance">
          <con:restRequest name="GET" id="5fe4087b-3b0b-4064-9f0a-7255a33e444d" mediaType="application/json">
            <con:settings>
              <con:setting id="com.eviware.soapui.impl.wsdl.WsdlRequest@request-headers">&lt;xml-fragment/></con:setting>
            </con:settings>
            <con:endpoint>https://petstore.swagger.io</con:endpoint>
            <con:request/>
            <con:originalUri>https://petstore.swagger.io/v2/pet/findByStatus</con:originalUri>
            <con:assertion type="Valid HTTP Status Codes" id="9c9772d4-2f8b-4538-8b8f-33ca3d98aa9d" name="Valid HTTP Status Codes">
              <con:settings/>
              <con:configuration>
                <codes>200</codes>
              </con:configuration>
            </con:assertion>
            <con:credentials>
              <con:selectedAuthProfile>No Authorization</con:selectedAuthProfile>
              <con:authType>No Authorization</con:authType>
            </con:credentials>
            <con:jmsConfig JMSDeliveryMode="PERSISTENT"/>
            <con:parameters>
              <con:entry key="ststus" value="available"/>
            </con:parameters>
            <con:parameterOrder>
              <con:entry>ststus</con:entry>
            </con:parameterOrder>
          </con:restRequest>
        </con:config>
      </con:testStep>
      <con:testStep type="restrequest" name="DELETE" id="da148b39-3432-4300-870f-75fe1989cab9">
        <con:settings/>
        <con:config service="https://petstore.swagger.io" resourcePath="/v2/pet/{petId}" methodName="PetId" xsi:type="con:RestRequestStep" xmlns:xsi="http://www.w3.org/2001/XMLSchema-instance">
          <con:restRequest name="DELETE" id="9a8337f8-40e9-4ff5-bbcd-0dd6bfb304bc" mediaType="application/json" postQueryString="false">
            <con:settings>
              <con:setting id="com.eviware.soapui.impl.wsdl.WsdlRequest@request-headers">&lt;xml-fragment/></con:setting>
            </con:settings>
            <con:endpoint>https://petstore.swagger.io</con:endpoint>
            <con:request/>
            <con:originalUri>https://petstore.swagger.io/v2/pet/77654</con:originalUri>
            <con:assertion type="Valid HTTP Status Codes" id="d378da30-2098-4e32-af80-bdd619699c55" name="Valid HTTP Status Codes">
              <con:settings/>
              <con:configuration>
                <codes>200</codes>
              </con:configuration>
            </con:assertion>
            <con:credentials>
              <con:selectedAuthProfile>No Authorization</con:selectedAuthProfile>
              <con:authType>No Authorization</con:authType>
            </con:credentials>
            <con:jmsConfig JMSDeliveryMode="PERSISTENT"/>
            <con:parameters>
              <con:entry key="petId" value="77654"/>
            </con:parameters>
            <con:parameterOrder>
              <con:entry>petId</con:entry>
            </con:parameterOrder>
          </con:restRequest>
        </con:config>
      </con:testStep>
      <con:properties/>
      <con:reportParameters/>
    </con:testCase>
    <con:testCase id="fe5ddc8b-359d-4e73-9239-4cfa70c12869" discardOkResults="false" failOnError="false" failTestCaseOnErrors="true" keepSession="false" name="Data Driven Test Case" searchProperties="true" timeout="0">
      <con:settings/>
      <con:testStep type="datasource" name="DataSource" id="3f91f8be-2d2d-44f9-aed2-d444adf9b428">
        <con:settings>
          <con:setting id="com.eviware.soapui.impl.wsdl.teststeps.datasource.DataSourceContainer@prepared-properties">&lt;xml-fragment/></con:setting>
        </con:settings>
        <con:config xsi:type="con:DataSourceStep" xmlns:xsi="http://www.w3.org/2001/XMLSchema-instance">
          <con:dataSource type="JDBC">
            <con:configuration>
              <driver>com.mysql.jdbc.Driver</driver>
              <connstr>jdbc:mysql://db4free.net:3306/fstm1db?user=fstm1db&amp;password=PASS_VALUE</connstr>
              <pass>6Y6NowPybq</pass>
              <Connection>FSTDB</Connection>
              <query>SELECT * FROM petData;</query>
              <fetchSize/>
              <stored-procedure>false</stored-procedure>
            </con:configuration>
          </con:dataSource>
          <con:shared>true</con:shared>
          <con:restartShared>true</con:restartShared>
          <con:property>petId</con:property>
          <con:property>petName</con:property>
          <con:property>petStatus</con:property>
          <con:restartOnRun>true</con:restartOnRun>
          <con:stopDatasourceExhausted>false</con:stopDatasourceExhausted>
        </con:config>
      </con:testStep>
      <con:testStep type="restrequest" name="POST" id="3e33a88b-5810-4788-9a6d-b84b5eb3fb8c">
        <con:settings/>
        <con:config service="https://petstore.swagger.io" resourcePath="/v2/pet" methodName="Pet" xsi:type="con:RestRequestStep" xmlns:xsi="http://www.w3.org/2001/XMLSchema-instance">
          <con:restRequest name="POST" id="28d15efd-6261-4047-bbc4-8a06c8f56396" mediaType="application/json" postQueryString="false">
            <con:settings>
              <con:setting id="com.eviware.soapui.impl.wsdl.WsdlRequest@request-headers">&lt;xml-fragment/></con:setting>
            </con:settings>
            <con:endpoint>https://petstore.swagger.io</con:endpoint>
            <con:request>{
    "id": ${DataSource#petId},
    "name": "${DataSource#petName}",
    "status":"${DataSource#petStatus}"
}</con:request>
            <con:originalUri>https://petstore.swagger.io/v2/pet</con:originalUri>
            <con:assertion type="Valid HTTP Status Codes" id="da4561b1-0e77-4ef5-a0b5-2a9a97d34f49" name="Valid HTTP Status Codes">
              <con:settings/>
              <con:configuration>
                <codes>200</codes>
              </con:configuration>
            </con:assertion>
            <con:credentials>
              <con:selectedAuthProfile>No Authorization</con:selectedAuthProfile>
              <con:authType>No Authorization</con:authType>
            </con:credentials>
            <con:jmsConfig JMSDeliveryMode="PERSISTENT"/>
            <con:parameters/>
          </con:restRequest>
        </con:config>
      </con:testStep>
      <con:testStep type="transfer" name="Property Transfer" id="991ea9d7-a015-4b12-b9b8-ce61e96b65e6">
        <con:settings/>
        <con:config xsi:type="con:PropertyTransfersStep" xmlns:xsi="http://www.w3.org/2001/XMLSchema-instance">
          <con:transfers setNullOnMissingSource="true" transferTextContent="true" failOnError="true" ignoreEmpty="false" transferToAll="false" entitize="false" transferChildNodes="false">
            <con:name>statusTransfer</con:name>
            <con:sourceType>Response</con:sourceType>
            <con:sourceStep>POST</con:sourceStep>
            <con:sourcePath>$['status']</con:sourcePath>
            <con:targetType>ststus</con:targetType>
            <con:targetStep>GET</con:targetStep>
            <con:targetPath/>
            <con:type>JSONPATH</con:type>
            <con:upgraded>true</con:upgraded>
          </con:transfers>
          <con:transfers setNullOnMissingSource="true" transferTextContent="true" failOnError="true" ignoreEmpty="false" transferToAll="false" entitize="false" transferChildNodes="false">
            <con:name>idTransfer</con:name>
            <con:sourceType>Response</con:sourceType>
            <con:sourceStep>POST</con:sourceStep>
            <con:sourcePath>$['id']</con:sourcePath>
            <con:targetType>petId</con:targetType>
            <con:targetStep>DELETE</con:targetStep>
            <con:type>JSONPATH</con:type>
            <con:upgraded>true</con:upgraded>
          </con:transfers>
        </con:config>
      </con:testStep>
      <con:testStep type="restrequest" name="GET" id="9b4a2579-7437-412d-acb5-a69b1b43199b">
        <con:settings/>
        <con:config service="https://petstore.swagger.io" resourcePath="/v2/pet/findByStatus" methodName="FindByStatus" xsi:type="con:RestRequestStep" xmlns:xsi="http://www.w3.org/2001/XMLSchema-instance">
          <con:restRequest name="GET" id="5fe4087b-3b0b-4064-9f0a-7255a33e444d" mediaType="application/json">
            <con:settings>
              <con:setting id="com.eviware.soapui.impl.wsdl.WsdlRequest@request-headers">&lt;xml-fragment/></con:setting>
            </con:settings>
            <con:endpoint>https://petstore.swagger.io</con:endpoint>
            <con:request/>
            <con:originalUri>https://petstore.swagger.io/v2/pet/findByStatus</con:originalUri>
            <con:assertion type="Valid HTTP Status Codes" id="9c9772d4-2f8b-4538-8b8f-33ca3d98aa9d" name="Valid HTTP Status Codes">
              <con:settings/>
              <con:configuration>
                <codes>200</codes>
              </con:configuration>
            </con:assertion>
            <con:credentials>
              <con:selectedAuthProfile>No Authorization</con:selectedAuthProfile>
              <con:authType>No Authorization</con:authType>
            </con:credentials>
            <con:jmsConfig JMSDeliveryMode="PERSISTENT"/>
            <con:parameters/>
            <con:parameterOrder>
              <con:entry>ststus</con:entry>
            </con:parameterOrder>
          </con:restRequest>
        </con:config>
      </con:testStep>
      <con:testStep type="restrequest" name="DELETE" id="05fb58dd-b1c1-4024-8f9b-97eb71608e22">
        <con:settings/>
        <con:config service="https://petstore.swagger.io" resourcePath="/v2/pet/{petId}" methodName="PetId" xsi:type="con:RestRequestStep" xmlns:xsi="http://www.w3.org/2001/XMLSchema-instance">
          <con:restRequest name="DELETE" id="9a8337f8-40e9-4ff5-bbcd-0dd6bfb304bc" mediaType="application/json" postQueryString="false">
            <con:settings>
              <con:setting id="com.eviware.soapui.impl.wsdl.WsdlRequest@request-headers">&lt;xml-fragment/></con:setting>
            </con:settings>
            <con:endpoint>https://petstore.swagger.io</con:endpoint>
            <con:request/>
            <con:originalUri>https://petstore.swagger.io/v2/pet/77654</con:originalUri>
            <con:assertion type="Valid HTTP Status Codes" id="d378da30-2098-4e32-af80-bdd619699c55" name="Valid HTTP Status Codes">
              <con:settings/>
              <con:configuration>
                <codes>200</codes>
              </con:configuration>
            </con:assertion>
            <con:credentials>
              <con:selectedAuthProfile>No Authorization</con:selectedAuthProfile>
              <con:authType>No Authorization</con:authType>
            </con:credentials>
            <con:jmsConfig JMSDeliveryMode="PERSISTENT"/>
            <con:parameters>
              <con:entry key="petId" value="789"/>
            </con:parameters>
            <con:parameterOrder>
              <con:entry>petId</con:entry>
            </con:parameterOrder>
          </con:restRequest>
        </con:config>
      </con:testStep>
      <con:testStep type="datasourceloop" name="Data Source Loop" id="56542408-8a01-4fe3-be41-14e48bc682db">
        <con:settings/>
        <con:config>
          <dataSourceStep>DataSource</dataSourceStep>
          <targetStep>POST</targetStep>
          <discardResults>true</discardResults>
        </con:config>
      </con:testStep>
      <con:properties/>
      <con:reportParameters/>
    </con:testCase>
    <con:properties/>
    <con:reportParameters/>
  </con:testSuite>
  <con:requirements/>
  <con:properties/>
  <con:wssContainer/>
  <con:databaseConnectionContainer>
    <con:databaseConnection>
      <con:name>FSTDB</con:name>
      <con:driver>com.mysql.jdbc.Driver</con:driver>
      <con:connectionString>jdbc:mysql://db4free.net:3306/fstm1db?user=fstm1db&amp;password=PASS_VALUE</con:connectionString>
      <con:password>6Y6NowPybq</con:password>
      <con:connectionProperties/>
    </con:databaseConnection>
  </con:databaseConnectionContainer>
  <con:jmsConnectionContainer/>
  <con:oAuth2ProfileContainer/>
  <con:oAuth1ProfileContainer/>
  <con:reporting>
    <con:xmlTemplates/>
    <con:parameters/>
  </con:reporting>
  <con:eventHandlers type="RequestFilter.filterRequest" name="RequestFilter.filterRequest">
    <con:script>// Sample event script to add custom HTTP header to all outgoing REST, SOAP and HTTP(S) calls
// This code is often used for adding custom authentication to ReadyAPI functional tests

// If hardcoding the token, uncomment and change line 5
// token = '4567'

// If your token is parameterized in Project level custom property, uncomment line 8
// token = request.parent.testCase.testSuite.project.getProperty('auth_token').getValue()

// To modify all outgoing calls, remove comments from lines 11 to 16
// headers = request.requestHeaders
// if (headers.containsKey('auth_token2') == false) {
//   headers.put('auth_token2', token)
//   request.requestHeaders = headers
// }</con:script>
  </con:eventHandlers>
  <con:eventHandlers type="TestRunListener.afterStep" name="TestRunListener.afterStep">
    <con:script>// Save all test step results into files
// Change the directory path in line 5 to a location where you want to store details
// then uncomment lines 5 to 10

// filePath = 'C:\\tempOutputDirectory\\'
// fos = new java.io.FileOutputStream(filePath + testStepResult.testStep.label + '.txt', true)
// pw = new java.io.PrintWriter(fos)
// testStepResult.writeTo(pw)
// pw.close()
// fos.close()</con:script>
  </con:eventHandlers>
  <con:authRepository/>
  <con:tags/>
</con:soapui-project>
